bing_rewards/__init__.py
bing_rewards/__main__.py
bing_rewards/options.py
bing_rewards/data/keywords.txt
bing_rewards-3.2.1.dist-info/METADATA
bing_rewards-3.2.1.dist-info/WHEEL
bing_rewards-3.2.1.dist-info/entry_points.txt
bing_rewards-3.2.1.dist-info/licenses/LICENSE
bing_rewards-3.2.1.dist-info/RECORD
