Metadata-Version: 2.4
Name: bing-rewards
Version: 3.2.1
Summary: Perform automated Bing Rewards searches
Project-URL: Source, https://github.com/jack-mil/bing-rewards
Project-URL: Issues, https://github.com/jack-mil/bing-rewards/issues
Project-URL: Changelog, https://github.com/jack-mil/bing-rewards/CHANGELOG.md
Author-email: jack-mil <62065280+jack-mil@users.noreply.github.com>
License-Expression: MIT
License-File: LICENSE
Keywords: automation,bing,pynput,search
Classifier: Intended Audience :: End Users/Desktop
Classifier: Operating System :: Microsoft :: Windows
Classifier: Operating System :: POSIX :: Linux
Classifier: Programming Language :: Python :: 3 :: Only
Classifier: Programming Language :: Python :: 3.10
Classifier: Programming Language :: Python :: 3.11
Classifier: Programming Language :: Python :: 3.12
Classifier: Programming Language :: Python :: 3.13
Classifier: Programming Language :: Python :: 3.14
Classifier: Topic :: Utilities
Requires-Python: >=3.10
Requires-Dist: pynput~=1.8
